k_vision/__init__.py
k_vision/text.py
k_vision/visual.py
k_vision/fonts/OpenSans-Semibold.ttf
k_vision/fonts/fa-solid-900.ttf
k_vision-0.1.8.dist-info/DESCRIPTION.rst
k_vision-0.1.8.dist-info/METADATA
k_vision-0.1.8.dist-info/RECORD
k_vision-0.1.8.dist-info/WHEEL
k_vision-0.1.8.dist-info/metadata.json
k_vision-0.1.8.dist-info/top_level.txt
