Metadata-Version: 2.0
Name: k-vision
Version: 0.1.8
Summary: Computer Vision tools and utility scripts.
Home-page: https://github.com/krinj/k-vision
Author: Jakrin Juangbhanich
Author-email: juangbhanich.k@gmail.com
License: UNKNOWN
Platform: UNKNOWN
Classifier: Programming Language :: Python :: 3.6
Requires-Dist: k-util
Requires-Dist: numpy
Requires-Dist: opencv-python
Requires-Dist: pillow
